coregenai/__init__.py
coregenai/async_chat.py
coregenai-0.2.0.dist-info/METADATA
coregenai-0.2.0.dist-info/WHEEL
coregenai-0.2.0.dist-info/RECORD
