Metadata-Version: 2.4
Name: coregenai
Version: 0.2.0
Summary: CoreGenAI is the unified Python SDK for Google's Generative AI that eliminates confusion, handles complexity, and just works.
Author-email: Saadman Rafat <saadman@outlook.com>
Keywords: ai,gemini,genai,generative-ai,google,llm,vertex-ai
Classifier: Development Status :: 4 - Beta
Classifier: Intended Audience :: Developers
Classifier: License :: OSI Approved :: MIT License
Classifier: Programming Language :: Python :: 3.11
Classifier: Programming Language :: Python :: 3.12
Classifier: Topic :: Software Development :: Libraries :: Python Modules
Requires-Python: >=3.10
Requires-Dist: google-genai>=1.50.1
Requires-Dist: pydantic-settings>=2.12.0
Requires-Dist: pydantic>=2.12.4
Requires-Dist: pytest-asyncio>=1.3.0
